Metadata-Version: 2.1
Name: python-edotenv
Version: 0.1.0
Summary: Save and load environmental variables using encrypted .env files
Home-page: https://github.com/rrwen/python-edotenv
Author: Richard Wen
Author-email: rrwen.dev@gmail.com
License: UNKNOWN
Project-URL: Bug Tracker, https://github.com/rrwen/python-edotenv/issues
Platform: UNKNOWN
Classifier: Programming Language :: Python :: 3
Classifier: License :: OSI Approved :: MIT License
Classifier: Operating System :: OS Independent
Requires-Python: >=3.8
License-File: LICENSE
